{"nodes": [{"id": "f_all_cording_klens_v2_klens_backend_python_app_utils_validation_py", "label": "validation.py", "file_type": "code", "source_file": "F:\\All\\CORDING\\KLENS-V2\\KLENS\\backend-python\\app\\utils\\validation.py", "source_location": "L1"}, {"id": "validation_sanitize_text", "label": "sanitize_text()", "file_type": "code", "source_file": "F:\\All\\CORDING\\KLENS-V2\\KLENS\\backend-python\\app\\utils\\validation.py", "source_location": "L47"}, {"id": "validation_validate_no_xss", "label": "validate_no_xss()", "file_type": "code", "source_file": "F:\\All\\CORDING\\KLENS-V2\\KLENS\\backend-python\\app\\utils\\validation.py", "source_location": "L71"}, {"id": "validation_validate_email_address", "label": "validate_email_address()", "file_type": "code", "source_file": "F:\\All\\CORDING\\KLENS-V2\\KLENS\\backend-python\\app\\utils\\validation.py", "source_location": "L86"}, {"id": "validation_validate_password_strength", "label": "validate_password_strength()", "file_type": "code", "source_file": "F:\\All\\CORDING\\KLENS-V2\\KLENS\\backend-python\\app\\utils\\validation.py", "source_location": "L102"}, {"id": "validation_validate_filename", "label": "validate_filename()", "file_type": "code", "source_file": "F:\\All\\CORDING\\KLENS-V2\\KLENS\\backend-python\\app\\utils\\validation.py", "source_location": "L140"}, {"id": "validation_validate_json_object", "label": "validate_json_object()", "file_type": "code", "source_file": "F:\\All\\CORDING\\KLENS-V2\\KLENS\\backend-python\\app\\utils\\validation.py", "source_location": "L164"}, {"id": "validation_strictbasemodel", "label": "StrictBaseModel", "file_type": "code", "source_file": "F:\\All\\CORDING\\KLENS-V2\\KLENS\\backend-python\\app\\utils\\validation.py", "source_location": "L194"}, {"id": "basemodel", "label": "BaseModel", "file_type": "code", "source_file": "", "source_location": ""}, {"id": "validation_config", "label": "Config", "file_type": "code", "source_file": "F:\\All\\CORDING\\KLENS-V2\\KLENS\\backend-python\\app\\utils\\validation.py", "source_location": "L199"}, {"id": "validation_validatedemail", "label": "ValidatedEmail", "file_type": "code", "source_file": "F:\\All\\CORDING\\KLENS-V2\\KLENS\\backend-python\\app\\utils\\validation.py", "source_location": "L208"}, {"id": "validation_validate_email_field", "label": "validate_email_field()", "file_type": "code", "source_file": "F:\\All\\CORDING\\KLENS-V2\\KLENS\\backend-python\\app\\utils\\validation.py", "source_location": "L219"}, {"id": "validation_validatedpassword", "label": "ValidatedPassword", "file_type": "code", "source_file": "F:\\All\\CORDING\\KLENS-V2\\KLENS\\backend-python\\app\\utils\\validation.py", "source_location": "L223"}, {"id": "validation_validate_password_field", "label": "validate_password_field()", "file_type": "code", "source_file": "F:\\All\\CORDING\\KLENS-V2\\KLENS\\backend-python\\app\\utils\\validation.py", "source_location": "L234"}, {"id": "validation_validatedtext", "label": "ValidatedText", "file_type": "code", "source_file": "F:\\All\\CORDING\\KLENS-V2\\KLENS\\backend-python\\app\\utils\\validation.py", "source_location": "L238"}, {"id": "validation_validate_text_field", "label": "validate_text_field()", "file_type": "code", "source_file": "F:\\All\\CORDING\\KLENS-V2\\KLENS\\backend-python\\app\\utils\\validation.py", "source_location": "L249"}, {"id": "validation_validatedsearchquery", "label": "ValidatedSearchQuery", "file_type": "code", "source_file": "F:\\All\\CORDING\\KLENS-V2\\KLENS\\backend-python\\app\\utils\\validation.py", "source_location": "L254"}, {"id": "validation_validate_query_field", "label": "validate_query_field()", "file_type": "code", "source_file": "F:\\All\\CORDING\\KLENS-V2\\KLENS\\backend-python\\app\\utils\\validation.py", "source_location": "L271"}, {"id": "validation_validatedchatmessage", "label": "ValidatedChatMessage", "file_type": "code", "source_file": "F:\\All\\CORDING\\KLENS-V2\\KLENS\\backend-python\\app\\utils\\validation.py", "source_location": "L276"}, {"id": "validation_validate_message_field", "label": "validate_message_field()", "file_type": "code", "source_file": "F:\\All\\CORDING\\KLENS-V2\\KLENS\\backend-python\\app\\utils\\validation.py", "source_location": "L287"}, {"id": "validation_validatedfilename", "label": "ValidatedFilename", "file_type": "code", "source_file": "F:\\All\\CORDING\\KLENS-V2\\KLENS\\backend-python\\app\\utils\\validation.py", "source_location": "L292"}, {"id": "validation_validate_filename_field", "label": "validate_filename_field()", "file_type": "code", "source_file": "F:\\All\\CORDING\\KLENS-V2\\KLENS\\backend-python\\app\\utils\\validation.py", "source_location": "L303"}, {"id": "validation_validatedname", "label": "ValidatedName", "file_type": "code", "source_file": "F:\\All\\CORDING\\KLENS-V2\\KLENS\\backend-python\\app\\utils\\validation.py", "source_location": "L307"}, {"id": "validation_validate_name_field", "label": "validate_name_field()", "file_type": "code", "source_file": "F:\\All\\CORDING\\KLENS-V2\\KLENS\\backend-python\\app\\utils\\validation.py", "source_location": "L318"}, {"id": "validation_validatedpin", "label": "ValidatedPIN", "file_type": "code", "source_file": "F:\\All\\CORDING\\KLENS-V2\\KLENS\\backend-python\\app\\utils\\validation.py", "source_location": "L323"}, {"id": "validation_validate_pin_field", "label": "validate_pin_field()", "file_type": "code", "source_file": "F:\\All\\CORDING\\KLENS-V2\\KLENS\\backend-python\\app\\utils\\validation.py", "source_location": "L334"}, {"id": "validation_validate_user_role", "label": "validate_user_role()", "file_type": "code", "source_file": "F:\\All\\CORDING\\KLENS-V2\\KLENS\\backend-python\\app\\utils\\validation.py", "source_location": "L342"}, {"id": "validation_validate_shift_status", "label": "validate_shift_status()", "file_type": "code", "source_file": "F:\\All\\CORDING\\KLENS-V2\\KLENS\\backend-python\\app\\utils\\validation.py", "source_location": "L360"}, {"id": "validation_validate_document_status", "label": "validate_document_status()", "file_type": "code", "source_file": "F:\\All\\CORDING\\KLENS-V2\\KLENS\\backend-python\\app\\utils\\validation.py", "source_location": "L376"}, {"id": "validation_rationale_1", "label": "Input Validation and Sanitization Utilities for K-LENS API  OWASP Best Practic", "file_type": "rationale", "source_file": "F:\\All\\CORDING\\KLENS-V2\\KLENS\\backend-python\\app\\utils\\validation.py", "source_location": "L1"}, {"id": "validation_rationale_48", "label": "Sanitize user-provided text to prevent XSS attacks.          Args:         te", "file_type": "rationale", "source_file": "F:\\All\\CORDING\\KLENS-V2\\KLENS\\backend-python\\app\\utils\\validation.py", "source_location": "L48"}, {"id": "validation_rationale_72", "label": "Validate that text doesn't contain XSS patterns.     Raises ValueError if XSS d", "file_type": "rationale", "source_file": "F:\\All\\CORDING\\KLENS-V2\\KLENS\\backend-python\\app\\utils\\validation.py", "source_location": "L72"}, {"id": "validation_rationale_87", "label": "Validate email address format and deliverability.     Raises ValueError if inva", "file_type": "rationale", "source_file": "F:\\All\\CORDING\\KLENS-V2\\KLENS\\backend-python\\app\\utils\\validation.py", "source_location": "L87"}, {"id": "validation_rationale_103", "label": "Validate password meets minimum security requirements.          Requirements:", "file_type": "rationale", "source_file": "F:\\All\\CORDING\\KLENS-V2\\KLENS\\backend-python\\app\\utils\\validation.py", "source_location": "L103"}, {"id": "validation_rationale_141", "label": "Validate filename to prevent path traversal and other attacks.          Raises", "file_type": "rationale", "source_file": "F:\\All\\CORDING\\KLENS-V2\\KLENS\\backend-python\\app\\utils\\validation.py", "source_location": "L141"}, {"id": "validation_rationale_165", "label": "Validate JSON object to prevent deeply nested structures (DoS attack).", "file_type": "rationale", "source_file": "F:\\All\\CORDING\\KLENS-V2\\KLENS\\backend-python\\app\\utils\\validation.py", "source_location": "L165"}, {"id": "validation_rationale_195", "label": "Base model with strict validation settings.     Rejects extra fields to prevent", "file_type": "rationale", "source_file": "F:\\All\\CORDING\\KLENS-V2\\KLENS\\backend-python\\app\\utils\\validation.py", "source_location": "L195"}, {"id": "validation_rationale_209", "label": "Email validation model", "file_type": "rationale", "source_file": "F:\\All\\CORDING\\KLENS-V2\\KLENS\\backend-python\\app\\utils\\validation.py", "source_location": "L209"}, {"id": "validation_rationale_224", "label": "Password validation model", "file_type": "rationale", "source_file": "F:\\All\\CORDING\\KLENS-V2\\KLENS\\backend-python\\app\\utils\\validation.py", "source_location": "L224"}, {"id": "validation_rationale_239", "label": "Generic text validation model", "file_type": "rationale", "source_file": "F:\\All\\CORDING\\KLENS-V2\\KLENS\\backend-python\\app\\utils\\validation.py", "source_location": "L239"}, {"id": "validation_rationale_255", "label": "Search query validation", "file_type": "rationale", "source_file": "F:\\All\\CORDING\\KLENS-V2\\KLENS\\backend-python\\app\\utils\\validation.py", "source_location": "L255"}, {"id": "validation_rationale_277", "label": "Chat message validation", "file_type": "rationale", "source_file": "F:\\All\\CORDING\\KLENS-V2\\KLENS\\backend-python\\app\\utils\\validation.py", "source_location": "L277"}, {"id": "validation_rationale_308", "label": "Name validation (user names, department names, etc.)", "file_type": "rationale", "source_file": "F:\\All\\CORDING\\KLENS-V2\\KLENS\\backend-python\\app\\utils\\validation.py", "source_location": "L308"}, {"id": "validation_rationale_324", "label": "PIN validation (4-6 digits)", "file_type": "rationale", "source_file": "F:\\All\\CORDING\\KLENS-V2\\KLENS\\backend-python\\app\\utils\\validation.py", "source_location": "L324"}, {"id": "validation_rationale_343", "label": "Validate user role against allowed values", "file_type": "rationale", "source_file": "F:\\All\\CORDING\\KLENS-V2\\KLENS\\backend-python\\app\\utils\\validation.py", "source_location": "L343"}, {"id": "validation_rationale_361", "label": "Validate shift status against allowed values", "file_type": "rationale", "source_file": "F:\\All\\CORDING\\KLENS-V2\\KLENS\\backend-python\\app\\utils\\validation.py", "source_location": "L361"}, {"id": "validation_rationale_377", "label": "Validate document status against allowed values", "file_type": "rationale", "source_file": "F:\\All\\CORDING\\KLENS-V2\\KLENS\\backend-python\\app\\utils\\validation.py", "source_location": "L377"}], "edges": [{"source": "f_all_cording_klens_v2_klens_backend_python_app_utils_validation_py", "target": "pydantic", "relation": "imports_from", "confidence": "EXTRACTED", "source_file": "F:\\All\\CORDING\\KLENS-V2\\KLENS\\backend-python\\app\\utils\\validation.py", "source_location": "L12", "weight": 1.0}, {"source": "f_all_cording_klens_v2_klens_backend_python_app_utils_validation_py", "target": "typing", "relation": "imports_from", "confidence": "EXTRACTED", "source_file": "F:\\All\\CORDING\\KLENS-V2\\KLENS\\backend-python\\app\\utils\\validation.py", "source_location": "L13", "weight": 1.0}, {"source": "f_all_cording_klens_v2_klens_backend_python_app_utils_validation_py", "target": "re", "relation": "imports", "confidence": "EXTRACTED", "source_file": "F:\\All\\CORDING\\KLENS-V2\\KLENS\\backend-python\\app\\utils\\validation.py", "source_location": "L14", "weight": 1.0}, {"source": "f_all_cording_klens_v2_klens_backend_python_app_utils_validation_py", "target": "html", "relation": "imports", "confidence": "EXTRACTED", "source_file": "F:\\All\\CORDING\\KLENS-V2\\KLENS\\backend-python\\app\\utils\\validation.py", "source_location": "L15", "weight": 1.0}, {"source": "f_all_cording_klens_v2_klens_backend_python_app_utils_validation_py", "target": "email_validator", "relation": "imports_from", "confidence": "EXTRACTED", "source_file": "F:\\All\\CORDING\\KLENS-V2\\KLENS\\backend-python\\app\\utils\\validation.py", "source_location": "L16", "weight": 1.0}, {"source": "f_all_cording_klens_v2_klens_backend_python_app_utils_validation_py", "target": "validation_sanitize_text", "relation": "contains", "confidence": "EXTRACTED", "source_file": "F:\\All\\CORDING\\KLENS-V2\\KLENS\\backend-python\\app\\utils\\validation.py", "source_location": "L47", "weight": 1.0}, {"source": "f_all_cording_klens_v2_klens_backend_python_app_utils_validation_py", "target": "validation_validate_no_xss", "relation": "contains", "confidence": "EXTRACTED", "source_file": "F:\\All\\CORDING\\KLENS-V2\\KLENS\\backend-python\\app\\utils\\validation.py", "source_location": "L71", "weight": 1.0}, {"source": "f_all_cording_klens_v2_klens_backend_python_app_utils_validation_py", "target": "validation_validate_email_address", "relation": "contains", "confidence": "EXTRACTED", "source_file": "F:\\All\\CORDING\\KLENS-V2\\KLENS\\backend-python\\app\\utils\\validation.py", "source_location": "L86", "weight": 1.0}, {"source": "f_all_cording_klens_v2_klens_backend_python_app_utils_validation_py", "target": "validation_validate_password_strength", "relation": "contains", "confidence": "EXTRACTED", "source_file": "F:\\All\\CORDING\\KLENS-V2\\KLENS\\backend-python\\app\\utils\\validation.py", "source_location": "L102", "weight": 1.0}, {"source": "f_all_cording_klens_v2_klens_backend_python_app_utils_validation_py", "target": "validation_validate_filename", "relation": "contains", "confidence": "EXTRACTED", "source_file": "F:\\All\\CORDING\\KLENS-V2\\KLENS\\backend-python\\app\\utils\\validation.py", "source_location": "L140", "weight": 1.0}, {"source": "f_all_cording_klens_v2_klens_backend_python_app_utils_validation_py", "target": "validation_validate_json_object", "relation": "contains", "confidence": "EXTRACTED", "source_file": "F:\\All\\CORDING\\KLENS-V2\\KLENS\\backend-python\\app\\utils\\validation.py", "source_location": "L164", "weight": 1.0}, {"source": "f_all_cording_klens_v2_klens_backend_python_app_utils_validation_py", "target": "validation_strictbasemodel", "relation": "contains", "confidence": "EXTRACTED", "source_file": "F:\\All\\CORDING\\KLENS-V2\\KLENS\\backend-python\\app\\utils\\validation.py", "source_location": "L194", "weight": 1.0}, {"source": "validation_strictbasemodel", "target": "basemodel", "relation": "inherits", "confidence": "EXTRACTED", "source_file": "F:\\All\\CORDING\\KLENS-V2\\KLENS\\backend-python\\app\\utils\\validation.py", "source_location": "L194", "weight": 1.0}, {"source": "f_all_cording_klens_v2_klens_backend_python_app_utils_validation_py", "target": "validation_config", "relation": "contains", "confidence": "EXTRACTED", "source_file": "F:\\All\\CORDING\\KLENS-V2\\KLENS\\backend-python\\app\\utils\\validation.py", "source_location": "L199", "weight": 1.0}, {"source": "f_all_cording_klens_v2_klens_backend_python_app_utils_validation_py", "target": "validation_validatedemail", "relation": "contains", "confidence": "EXTRACTED", "source_file": "F:\\All\\CORDING\\KLENS-V2\\KLENS\\backend-python\\app\\utils\\validation.py", "source_location": "L208", "weight": 1.0}, {"source": "validation_validatedemail", "target": "validation_strictbasemodel", "relation": "inherits", "confidence": "EXTRACTED", "source_file": "F:\\All\\CORDING\\KLENS-V2\\KLENS\\backend-python\\app\\utils\\validation.py", "source_location": "L208", "weight": 1.0}, {"source": "f_all_cording_klens_v2_klens_backend_python_app_utils_validation_py", "target": "validation_validate_email_field", "relation": "contains", "confidence": "EXTRACTED", "source_file": "F:\\All\\CORDING\\KLENS-V2\\KLENS\\backend-python\\app\\utils\\validation.py", "source_location": "L219", "weight": 1.0}, {"source": "f_all_cording_klens_v2_klens_backend_python_app_utils_validation_py", "target": "validation_validatedpassword", "relation": "contains", "confidence": "EXTRACTED", "source_file": "F:\\All\\CORDING\\KLENS-V2\\KLENS\\backend-python\\app\\utils\\validation.py", "source_location": "L223", "weight": 1.0}, {"source": "validation_validatedpassword", "target": "validation_strictbasemodel", "relation": "inherits", "confidence": "EXTRACTED", "source_file": "F:\\All\\CORDING\\KLENS-V2\\KLENS\\backend-python\\app\\utils\\validation.py", "source_location": "L223", "weight": 1.0}, {"source": "f_all_cording_klens_v2_klens_backend_python_app_utils_validation_py", "target": "validation_validate_password_field", "relation": "contains", "confidence": "EXTRACTED", "source_file": "F:\\All\\CORDING\\KLENS-V2\\KLENS\\backend-python\\app\\utils\\validation.py", "source_location": "L234", "weight": 1.0}, {"source": "f_all_cording_klens_v2_klens_backend_python_app_utils_validation_py", "target": "validation_validatedtext", "relation": "contains", "confidence": "EXTRACTED", "source_file": "F:\\All\\CORDING\\KLENS-V2\\KLENS\\backend-python\\app\\utils\\validation.py", "source_location": "L238", "weight": 1.0}, {"source": "validation_validatedtext", "target": "validation_strictbasemodel", "relation": "inherits", "confidence": "EXTRACTED", "source_file": "F:\\All\\CORDING\\KLENS-V2\\KLENS\\backend-python\\app\\utils\\validation.py", "source_location": "L238", "weight": 1.0}, {"source": "f_all_cording_klens_v2_klens_backend_python_app_utils_validation_py", "target": "validation_validate_text_field", "relation": "contains", "confidence": "EXTRACTED", "source_file": "F:\\All\\CORDING\\KLENS-V2\\KLENS\\backend-python\\app\\utils\\validation.py", "source_location": "L249", "weight": 1.0}, {"source": "f_all_cording_klens_v2_klens_backend_python_app_utils_validation_py", "target": "validation_validatedsearchquery", "relation": "contains", "confidence": "EXTRACTED", "source_file": "F:\\All\\CORDING\\KLENS-V2\\KLENS\\backend-python\\app\\utils\\validation.py", "source_location": "L254", "weight": 1.0}, {"source": "validation_validatedsearchquery", "target": "validation_strictbasemodel", "relation": "inherits", "confidence": "EXTRACTED", "source_file": "F:\\All\\CORDING\\KLENS-V2\\KLENS\\backend-python\\app\\utils\\validation.py", "source_location": "L254", "weight": 1.0}, {"source": "f_all_cording_klens_v2_klens_backend_python_app_utils_validation_py", "target": "validation_validate_query_field", "relation": "contains", "confidence": "EXTRACTED", "source_file": "F:\\All\\CORDING\\KLENS-V2\\KLENS\\backend-python\\app\\utils\\validation.py", "source_location": "L271", "weight": 1.0}, {"source": "f_all_cording_klens_v2_klens_backend_python_app_utils_validation_py", "target": "validation_validatedchatmessage", "relation": "contains", "confidence": "EXTRACTED", "source_file": "F:\\All\\CORDING\\KLENS-V2\\KLENS\\backend-python\\app\\utils\\validation.py", "source_location": "L276", "weight": 1.0}, {"source": "validation_validatedchatmessage", "target": "validation_strictbasemodel", "relation": "inherits", "confidence": "EXTRACTED", "source_file": "F:\\All\\CORDING\\KLENS-V2\\KLENS\\backend-python\\app\\utils\\validation.py", "source_location": "L276", "weight": 1.0}, {"source": "f_all_cording_klens_v2_klens_backend_python_app_utils_validation_py", "target": "validation_validate_message_field", "relation": "contains", "confidence": "EXTRACTED", "source_file": "F:\\All\\CORDING\\KLENS-V2\\KLENS\\backend-python\\app\\utils\\validation.py", "source_location": "L287", "weight": 1.0}, {"source": "f_all_cording_klens_v2_klens_backend_python_app_utils_validation_py", "target": "validation_validatedfilename", "relation": "contains", "confidence": "EXTRACTED", "source_file": "F:\\All\\CORDING\\KLENS-V2\\KLENS\\backend-python\\app\\utils\\validation.py", "source_location": "L292", "weight": 1.0}, {"source": "validation_validatedfilename", "target": "validation_strictbasemodel", "relation": "inherits", "confidence": "EXTRACTED", "source_file": "F:\\All\\CORDING\\KLENS-V2\\KLENS\\backend-python\\app\\utils\\validation.py", "source_location": "L292", "weight": 1.0}, {"source": "f_all_cording_klens_v2_klens_backend_python_app_utils_validation_py", "target": "validation_validate_filename_field", "relation": "contains", "confidence": "EXTRACTED", "source_file": "F:\\All\\CORDING\\KLENS-V2\\KLENS\\backend-python\\app\\utils\\validation.py", "source_location": "L303", "weight": 1.0}, {"source": "f_all_cording_klens_v2_klens_backend_python_app_utils_validation_py", "target": "validation_validatedname", "relation": "contains", "confidence": "EXTRACTED", "source_file": "F:\\All\\CORDING\\KLENS-V2\\KLENS\\backend-python\\app\\utils\\validation.py", "source_location": "L307", "weight": 1.0}, {"source": "validation_validatedname", "target": "validation_strictbasemodel", "relation": "inherits", "confidence": "EXTRACTED", "source_file": "F:\\All\\CORDING\\KLENS-V2\\KLENS\\backend-python\\app\\utils\\validation.py", "source_location": "L307", "weight": 1.0}, {"source": "f_all_cording_klens_v2_klens_backend_python_app_utils_validation_py", "target": "validation_validate_name_field", "relation": "contains", "confidence": "EXTRACTED", "source_file": "F:\\All\\CORDING\\KLENS-V2\\KLENS\\backend-python\\app\\utils\\validation.py", "source_location": "L318", "weight": 1.0}, {"source": "f_all_cording_klens_v2_klens_backend_python_app_utils_validation_py", "target": "validation_validatedpin", "relation": "contains", "confidence": "EXTRACTED", "source_file": "F:\\All\\CORDING\\KLENS-V2\\KLENS\\backend-python\\app\\utils\\validation.py", "source_location": "L323", "weight": 1.0}, {"source": "validation_validatedpin", "target": "validation_strictbasemodel", "relation": "inherits", "confidence": "EXTRACTED", "source_file": "F:\\All\\CORDING\\KLENS-V2\\KLENS\\backend-python\\app\\utils\\validation.py", "source_location": "L323", "weight": 1.0}, {"source": "f_all_cording_klens_v2_klens_backend_python_app_utils_validation_py", "target": "validation_validate_pin_field", "relation": "contains", "confidence": "EXTRACTED", "source_file": "F:\\All\\CORDING\\KLENS-V2\\KLENS\\backend-python\\app\\utils\\validation.py", "source_location": "L334", "weight": 1.0}, {"source": "f_all_cording_klens_v2_klens_backend_python_app_utils_validation_py", "target": "validation_validate_user_role", "relation": "contains", "confidence": "EXTRACTED", "source_file": "F:\\All\\CORDING\\KLENS-V2\\KLENS\\backend-python\\app\\utils\\validation.py", "source_location": "L342", "weight": 1.0}, {"source": "f_all_cording_klens_v2_klens_backend_python_app_utils_validation_py", "target": "validation_validate_shift_status", "relation": "contains", "confidence": "EXTRACTED", "source_file": "F:\\All\\CORDING\\KLENS-V2\\KLENS\\backend-python\\app\\utils\\validation.py", "source_location": "L360", "weight": 1.0}, {"source": "f_all_cording_klens_v2_klens_backend_python_app_utils_validation_py", "target": "validation_validate_document_status", "relation": "contains", "confidence": "EXTRACTED", "source_file": "F:\\All\\CORDING\\KLENS-V2\\KLENS\\backend-python\\app\\utils\\validation.py", "source_location": "L376", "weight": 1.0}, {"source": "validation_validate_email_field", "target": "validation_validate_email_address", "relation": "calls", "confidence": "EXTRACTED", "source_file": "F:\\All\\CORDING\\KLENS-V2\\KLENS\\backend-python\\app\\utils\\validation.py", "source_location": "L220", "weight": 1.0}, {"source": "validation_validate_password_field", "target": "validation_validate_password_strength", "relation": "calls", "confidence": "EXTRACTED", "source_file": "F:\\All\\CORDING\\KLENS-V2\\KLENS\\backend-python\\app\\utils\\validation.py", "source_location": "L235", "weight": 1.0}, {"source": "validation_validate_text_field", "target": "validation_validate_no_xss", "relation": "calls", "confidence": "EXTRACTED", "source_file": "F:\\All\\CORDING\\KLENS-V2\\KLENS\\backend-python\\app\\utils\\validation.py", "source_location": "L250", "weight": 1.0}, {"source": "validation_validate_text_field", "target": "validation_sanitize_text", "relation": "calls", "confidence": "EXTRACTED", "source_file": "F:\\All\\CORDING\\KLENS-V2\\KLENS\\backend-python\\app\\utils\\validation.py", "source_location": "L251", "weight": 1.0}, {"source": "validation_validate_query_field", "target": "validation_validate_no_xss", "relation": "calls", "confidence": "EXTRACTED", "source_file": "F:\\All\\CORDING\\KLENS-V2\\KLENS\\backend-python\\app\\utils\\validation.py", "source_location": "L272", "weight": 1.0}, {"source": "validation_validate_query_field", "target": "validation_sanitize_text", "relation": "calls", "confidence": "EXTRACTED", "source_file": "F:\\All\\CORDING\\KLENS-V2\\KLENS\\backend-python\\app\\utils\\validation.py", "source_location": "L273", "weight": 1.0}, {"source": "validation_validate_message_field", "target": "validation_validate_no_xss", "relation": "calls", "confidence": "EXTRACTED", "source_file": "F:\\All\\CORDING\\KLENS-V2\\KLENS\\backend-python\\app\\utils\\validation.py", "source_location": "L288", "weight": 1.0}, {"source": "validation_validate_message_field", "target": "validation_sanitize_text", "relation": "calls", "confidence": "EXTRACTED", "source_file": "F:\\All\\CORDING\\KLENS-V2\\KLENS\\backend-python\\app\\utils\\validation.py", "source_location": "L289", "weight": 1.0}, {"source": "validation_validate_filename_field", "target": "validation_validate_filename", "relation": "calls", "confidence": "EXTRACTED", "source_file": "F:\\All\\CORDING\\KLENS-V2\\KLENS\\backend-python\\app\\utils\\validation.py", "source_location": "L304", "weight": 1.0}, {"source": "validation_validate_name_field", "target": "validation_validate_no_xss", "relation": "calls", "confidence": "EXTRACTED", "source_file": "F:\\All\\CORDING\\KLENS-V2\\KLENS\\backend-python\\app\\utils\\validation.py", "source_location": "L319", "weight": 1.0}, {"source": "validation_validate_name_field", "target": "validation_sanitize_text", "relation": "calls", "confidence": "EXTRACTED", "source_file": "F:\\All\\CORDING\\KLENS-V2\\KLENS\\backend-python\\app\\utils\\validation.py", "source_location": "L320", "weight": 1.0}, {"source": "validation_rationale_1", "target": "f_all_cording_klens_v2_klens_backend_python_app_utils_validation_py", "relation": "rationale_for", "confidence": "EXTRACTED", "source_file": "F:\\All\\CORDING\\KLENS-V2\\KLENS\\backend-python\\app\\utils\\validation.py", "source_location": "L1", "weight": 1.0}, {"source": "validation_rationale_48", "target": "validation_sanitize_text", "relation": "rationale_for", "confidence": "EXTRACTED", "source_file": "F:\\All\\CORDING\\KLENS-V2\\KLENS\\backend-python\\app\\utils\\validation.py", "source_location": "L48", "weight": 1.0}, {"source": "validation_rationale_72", "target": "validation_validate_no_xss", "relation": "rationale_for", "confidence": "EXTRACTED", "source_file": "F:\\All\\CORDING\\KLENS-V2\\KLENS\\backend-python\\app\\utils\\validation.py", "source_location": "L72", "weight": 1.0}, {"source": "validation_rationale_87", "target": "validation_validate_email_address", "relation": "rationale_for", "confidence": "EXTRACTED", "source_file": "F:\\All\\CORDING\\KLENS-V2\\KLENS\\backend-python\\app\\utils\\validation.py", "source_location": "L87", "weight": 1.0}, {"source": "validation_rationale_103", "target": "validation_validate_password_strength", "relation": "rationale_for", "confidence": "EXTRACTED", "source_file": "F:\\All\\CORDING\\KLENS-V2\\KLENS\\backend-python\\app\\utils\\validation.py", "source_location": "L103", "weight": 1.0}, {"source": "validation_rationale_141", "target": "validation_validate_filename", "relation": "rationale_for", "confidence": "EXTRACTED", "source_file": "F:\\All\\CORDING\\KLENS-V2\\KLENS\\backend-python\\app\\utils\\validation.py", "source_location": "L141", "weight": 1.0}, {"source": "validation_rationale_165", "target": "validation_validate_json_object", "relation": "rationale_for", "confidence": "EXTRACTED", "source_file": "F:\\All\\CORDING\\KLENS-V2\\KLENS\\backend-python\\app\\utils\\validation.py", "source_location": "L165", "weight": 1.0}, {"source": "validation_rationale_195", "target": "validation_strictbasemodel", "relation": "rationale_for", "confidence": "EXTRACTED", "source_file": "F:\\All\\CORDING\\KLENS-V2\\KLENS\\backend-python\\app\\utils\\validation.py", "source_location": "L195", "weight": 1.0}, {"source": "validation_rationale_209", "target": "validation_validatedemail", "relation": "rationale_for", "confidence": "EXTRACTED", "source_file": "F:\\All\\CORDING\\KLENS-V2\\KLENS\\backend-python\\app\\utils\\validation.py", "source_location": "L209", "weight": 1.0}, {"source": "validation_rationale_224", "target": "validation_validatedpassword", "relation": "rationale_for", "confidence": "EXTRACTED", "source_file": "F:\\All\\CORDING\\KLENS-V2\\KLENS\\backend-python\\app\\utils\\validation.py", "source_location": "L224", "weight": 1.0}, {"source": "validation_rationale_239", "target": "validation_validatedtext", "relation": "rationale_for", "confidence": "EXTRACTED", "source_file": "F:\\All\\CORDING\\KLENS-V2\\KLENS\\backend-python\\app\\utils\\validation.py", "source_location": "L239", "weight": 1.0}, {"source": "validation_rationale_255", "target": "validation_validatedsearchquery", "relation": "rationale_for", "confidence": "EXTRACTED", "source_file": "F:\\All\\CORDING\\KLENS-V2\\KLENS\\backend-python\\app\\utils\\validation.py", "source_location": "L255", "weight": 1.0}, {"source": "validation_rationale_277", "target": "validation_validatedchatmessage", "relation": "rationale_for", "confidence": "EXTRACTED", "source_file": "F:\\All\\CORDING\\KLENS-V2\\KLENS\\backend-python\\app\\utils\\validation.py", "source_location": "L277", "weight": 1.0}, {"source": "validation_rationale_308", "target": "validation_validatedname", "relation": "rationale_for", "confidence": "EXTRACTED", "source_file": "F:\\All\\CORDING\\KLENS-V2\\KLENS\\backend-python\\app\\utils\\validation.py", "source_location": "L308", "weight": 1.0}, {"source": "validation_rationale_324", "target": "validation_validatedpin", "relation": "rationale_for", "confidence": "EXTRACTED", "source_file": "F:\\All\\CORDING\\KLENS-V2\\KLENS\\backend-python\\app\\utils\\validation.py", "source_location": "L324", "weight": 1.0}, {"source": "validation_rationale_343", "target": "validation_validate_user_role", "relation": "rationale_for", "confidence": "EXTRACTED", "source_file": "F:\\All\\CORDING\\KLENS-V2\\KLENS\\backend-python\\app\\utils\\validation.py", "source_location": "L343", "weight": 1.0}, {"source": "validation_rationale_361", "target": "validation_validate_shift_status", "relation": "rationale_for", "confidence": "EXTRACTED", "source_file": "F:\\All\\CORDING\\KLENS-V2\\KLENS\\backend-python\\app\\utils\\validation.py", "source_location": "L361", "weight": 1.0}, {"source": "validation_rationale_377", "target": "validation_validate_document_status", "relation": "rationale_for", "confidence": "EXTRACTED", "source_file": "F:\\All\\CORDING\\KLENS-V2\\KLENS\\backend-python\\app\\utils\\validation.py", "source_location": "L377", "weight": 1.0}], "raw_calls": [{"caller_nid": "validation_sanitize_text", "callee": "escape", "source_file": "F:\\All\\CORDING\\KLENS-V2\\KLENS\\backend-python\\app\\utils\\validation.py", "source_location": "L62"}, {"caller_nid": "validation_sanitize_text", "callee": "strip", "source_file": "F:\\All\\CORDING\\KLENS-V2\\KLENS\\backend-python\\app\\utils\\validation.py", "source_location": "L62"}, {"caller_nid": "validation_sanitize_text", "callee": "len", "source_file": "F:\\All\\CORDING\\KLENS-V2\\KLENS\\backend-python\\app\\utils\\validation.py", "source_location": "L65"}, {"caller_nid": "validation_validate_no_xss", "callee": "search", "source_file": "F:\\All\\CORDING\\KLENS-V2\\KLENS\\backend-python\\app\\utils\\validation.py", "source_location": "L80"}, {"caller_nid": "validation_validate_no_xss", "callee": "ValueError", "source_file": "F:\\All\\CORDING\\KLENS-V2\\KLENS\\backend-python\\app\\utils\\validation.py", "source_location": "L81"}, {"caller_nid": "validation_validate_email_address", "callee": "len", "source_file": "F:\\All\\CORDING\\KLENS-V2\\KLENS\\backend-python\\app\\utils\\validation.py", "source_location": "L91"}, {"caller_nid": "validation_validate_email_address", "callee": "ValueError", "source_file": "F:\\All\\CORDING\\KLENS-V2\\KLENS\\backend-python\\app\\utils\\validation.py", "source_location": "L92"}, {"caller_nid": "validation_validate_email_address", "callee": "validate_email", "source_file": "F:\\All\\CORDING\\KLENS-V2\\KLENS\\backend-python\\app\\utils\\validation.py", "source_location": "L96"}, {"caller_nid": "validation_validate_email_address", "callee": "ValueError", "source_file": "F:\\All\\CORDING\\KLENS-V2\\KLENS\\backend-python\\app\\utils\\validation.py", "source_location": "L99"}, {"caller_nid": "validation_validate_email_address", "callee": "str", "source_file": "F:\\All\\CORDING\\KLENS-V2\\KLENS\\backend-python\\app\\utils\\validation.py", "source_location": "L99"}, {"caller_nid": "validation_validate_password_strength", "callee": "ValueError", "source_file": "F:\\All\\CORDING\\KLENS-V2\\KLENS\\backend-python\\app\\utils\\validation.py", "source_location": "L117"}, {"caller_nid": "validation_validate_password_strength", "callee": "len", "source_file": "F:\\All\\CORDING\\KLENS-V2\\KLENS\\backend-python\\app\\utils\\validation.py", "source_location": "L119"}, {"caller_nid": "validation_validate_password_strength", "callee": "ValueError", "source_file": "F:\\All\\CORDING\\KLENS-V2\\KLENS\\backend-python\\app\\utils\\validation.py", "source_location": "L120"}, {"caller_nid": "validation_validate_password_strength", "callee": "len", "source_file": "F:\\All\\CORDING\\KLENS-V2\\KLENS\\backend-python\\app\\utils\\validation.py", "source_location": "L122"}, {"caller_nid": "validation_validate_password_strength", "callee": "ValueError", "source_file": "F:\\All\\CORDING\\KLENS-V2\\KLENS\\backend-python\\app\\utils\\validation.py", "source_location": "L123"}, {"caller_nid": "validation_validate_password_strength", "callee": "search", "source_file": "F:\\All\\CORDING\\KLENS-V2\\KLENS\\backend-python\\app\\utils\\validation.py", "source_location": "L125"}, {"caller_nid": "validation_validate_password_strength", "callee": "ValueError", "source_file": "F:\\All\\CORDING\\KLENS-V2\\KLENS\\backend-python\\app\\utils\\validation.py", "source_location": "L126"}, {"caller_nid": "validation_validate_password_strength", "callee": "search", "source_file": "F:\\All\\CORDING\\KLENS-V2\\KLENS\\backend-python\\app\\utils\\validation.py", "source_location": "L128"}, {"caller_nid": "validation_validate_password_strength", "callee": "ValueError", "source_file": "F:\\All\\CORDING\\KLENS-V2\\KLENS\\backend-python\\app\\utils\\validation.py", "source_location": "L129"}, {"caller_nid": "validation_validate_password_strength", "callee": "search", "source_file": "F:\\All\\CORDING\\KLENS-V2\\KLENS\\backend-python\\app\\utils\\validation.py", "source_location": "L131"}, {"caller_nid": "validation_validate_password_strength", "callee": "ValueError", "source_file": "F:\\All\\CORDING\\KLENS-V2\\KLENS\\backend-python\\app\\utils\\validation.py", "source_location": "L132"}, {"caller_nid": "validation_validate_password_strength", "callee": "search", "source_file": "F:\\All\\CORDING\\KLENS-V2\\KLENS\\backend-python\\app\\utils\\validation.py", "source_location": "L134"}, {"caller_nid": "validation_validate_password_strength", "callee": "ValueError", "source_file": "F:\\All\\CORDING\\KLENS-V2\\KLENS\\backend-python\\app\\utils\\validation.py", "source_location": "L135"}, {"caller_nid": "validation_validate_filename", "callee": "ValueError", "source_file": "F:\\All\\CORDING\\KLENS-V2\\KLENS\\backend-python\\app\\utils\\validation.py", "source_location": "L147"}, {"caller_nid": "validation_validate_filename", "callee": "len", "source_file": "F:\\All\\CORDING\\KLENS-V2\\KLENS\\backend-python\\app\\utils\\validation.py", "source_location": "L149"}, {"caller_nid": "validation_validate_filename", "callee": "ValueError", "source_file": "F:\\All\\CORDING\\KLENS-V2\\KLENS\\backend-python\\app\\utils\\validation.py", "source_location": "L150"}, {"caller_nid": "validation_validate_filename", "callee": "ValueError", "source_file": "F:\\All\\CORDING\\KLENS-V2\\KLENS\\backend-python\\app\\utils\\validation.py", "source_location": "L154"}, {"caller_nid": "validation_validate_filename", "callee": "any", "source_file": "F:\\All\\CORDING\\KLENS-V2\\KLENS\\backend-python\\app\\utils\\validation.py", "source_location": "L158"}, {"caller_nid": "validation_validate_filename", "callee": "endswith", "source_file": "F:\\All\\CORDING\\KLENS-V2\\KLENS\\backend-python\\app\\utils\\validation.py", "source_location": "L158"}, {"caller_nid": "validation_validate_filename", "callee": "lower", "source_file": "F:\\All\\CORDING\\KLENS-V2\\KLENS\\backend-python\\app\\utils\\validation.py", "source_location": "L158"}, {"caller_nid": "validation_validate_filename", "callee": "ValueError", "source_file": "F:\\All\\CORDING\\KLENS-V2\\KLENS\\backend-python\\app\\utils\\validation.py", "source_location": "L159"}, {"caller_nid": "validation_validate_filename", "callee": "join", "source_file": "F:\\All\\CORDING\\KLENS-V2\\KLENS\\backend-python\\app\\utils\\validation.py", "source_location": "L159"}, {"caller_nid": "validation_validate_json_object", "callee": "ValueError", "source_file": "F:\\All\\CORDING\\KLENS-V2\\KLENS\\backend-python\\app\\utils\\validation.py", "source_location": "L171"}, {"caller_nid": "validation_validate_json_object", "callee": "isinstance", "source_file": "F:\\All\\CORDING\\KLENS-V2\\KLENS\\backend-python\\app\\utils\\validation.py", "source_location": "L173"}, {"caller_nid": "validation_validate_json_object", "callee": "len", "source_file": "F:\\All\\CORDING\\KLENS-V2\\KLENS\\backend-python\\app\\utils\\validation.py", "source_location": "L174"}, {"caller_nid": "validation_validate_json_object", "callee": "ValueError", "source_file": "F:\\All\\CORDING\\KLENS-V2\\KLENS\\backend-python\\app\\utils\\validation.py", "source_location": "L175"}, {"caller_nid": "validation_validate_json_object", "callee": "items", "source_file": "F:\\All\\CORDING\\KLENS-V2\\KLENS\\backend-python\\app\\utils\\validation.py", "source_location": "L179"}, {"caller_nid": "validation_validate_json_object", "callee": "isinstance", "source_file": "F:\\All\\CORDING\\KLENS-V2\\KLENS\\backend-python\\app\\utils\\validation.py", "source_location": "L182"}, {"caller_nid": "validation_validate_json_object", "callee": "len", "source_file": "F:\\All\\CORDING\\KLENS-V2\\KLENS\\backend-python\\app\\utils\\validation.py", "source_location": "L183"}, {"caller_nid": "validation_validate_json_object", "callee": "ValueError", "source_file": "F:\\All\\CORDING\\KLENS-V2\\KLENS\\backend-python\\app\\utils\\validation.py", "source_location": "L184"}, {"caller_nid": "validation_validate_pin_field", "callee": "match", "source_file": "F:\\All\\CORDING\\KLENS-V2\\KLENS\\backend-python\\app\\utils\\validation.py", "source_location": "L335"}, {"caller_nid": "validation_validate_pin_field", "callee": "ValueError", "source_file": "F:\\All\\CORDING\\KLENS-V2\\KLENS\\backend-python\\app\\utils\\validation.py", "source_location": "L336"}, {"caller_nid": "validation_validate_user_role", "callee": "upper", "source_file": "F:\\All\\CORDING\\KLENS-V2\\KLENS\\backend-python\\app\\utils\\validation.py", "source_location": "L353"}, {"caller_nid": "validation_validate_user_role", "callee": "ValueError", "source_file": "F:\\All\\CORDING\\KLENS-V2\\KLENS\\backend-python\\app\\utils\\validation.py", "source_location": "L355"}, {"caller_nid": "validation_validate_user_role", "callee": "join", "source_file": "F:\\All\\CORDING\\KLENS-V2\\KLENS\\backend-python\\app\\utils\\validation.py", "source_location": "L355"}, {"caller_nid": "validation_validate_shift_status", "callee": "upper", "source_file": "F:\\All\\CORDING\\KLENS-V2\\KLENS\\backend-python\\app\\utils\\validation.py", "source_location": "L369"}, {"caller_nid": "validation_validate_shift_status", "callee": "ValueError", "source_file": "F:\\All\\CORDING\\KLENS-V2\\KLENS\\backend-python\\app\\utils\\validation.py", "source_location": "L371"}, {"caller_nid": "validation_validate_shift_status", "callee": "join", "source_file": "F:\\All\\CORDING\\KLENS-V2\\KLENS\\backend-python\\app\\utils\\validation.py", "source_location": "L371"}, {"caller_nid": "validation_validate_document_status", "callee": "lower", "source_file": "F:\\All\\CORDING\\KLENS-V2\\KLENS\\backend-python\\app\\utils\\validation.py", "source_location": "L385"}, {"caller_nid": "validation_validate_document_status", "callee": "ValueError", "source_file": "F:\\All\\CORDING\\KLENS-V2\\KLENS\\backend-python\\app\\utils\\validation.py", "source_location": "L387"}, {"caller_nid": "validation_validate_document_status", "callee": "join", "source_file": "F:\\All\\CORDING\\KLENS-V2\\KLENS\\backend-python\\app\\utils\\validation.py", "source_location": "L387"}]}